wxyz/tpl_jinja/__init__.py
wxyz/tpl_jinja/_version.py
wxyz/tpl_jinja/base.py
wxyz/tpl_jinja/install.json
wxyz/tpl_jinja/widget_template.py
wxyz/tpl_jinja/js/LICENSE.txt
wxyz/tpl_jinja/js/README.md
wxyz/tpl_jinja/js/package.json
wxyz/tpl_jinja/labextension/package.json
wxyz/tpl_jinja/labextension/static/126.a36e2b63f2e19229bded.js
wxyz/tpl_jinja/labextension/static/126.a36e2b63f2e19229bded.js.LICENSE.txt
wxyz/tpl_jinja/labextension/static/333.4b8767a7cf8fba8ca76d.js
wxyz/tpl_jinja/labextension/static/568.9376be114c08878ade77.js
wxyz/tpl_jinja/labextension/static/920.f6a88f0e14db74ac57a0.js
wxyz/tpl_jinja/labextension/static/remoteEntry.8fc394d0f9814dd4dc28.js
wxyz/tpl_jinja/labextension/static/style.js
wxyz_tpl_jinja-0.5.1.data/data/share/jupyter/labextensions/@deathbeds/wxyz-tpl-nunjucks/install.json
wxyz_tpl_jinja-0.5.1.data/data/share/jupyter/labextensions/@deathbeds/wxyz-tpl-nunjucks/package.json
wxyz_tpl_jinja-0.5.1.data/data/share/jupyter/labextensions/@deathbeds/wxyz-tpl-nunjucks/static/126.a36e2b63f2e19229bded.js
wxyz_tpl_jinja-0.5.1.data/data/share/jupyter/labextensions/@deathbeds/wxyz-tpl-nunjucks/static/126.a36e2b63f2e19229bded.js.LICENSE.txt
wxyz_tpl_jinja-0.5.1.data/data/share/jupyter/labextensions/@deathbeds/wxyz-tpl-nunjucks/static/333.4b8767a7cf8fba8ca76d.js
wxyz_tpl_jinja-0.5.1.data/data/share/jupyter/labextensions/@deathbeds/wxyz-tpl-nunjucks/static/568.9376be114c08878ade77.js
wxyz_tpl_jinja-0.5.1.data/data/share/jupyter/labextensions/@deathbeds/wxyz-tpl-nunjucks/static/920.f6a88f0e14db74ac57a0.js
wxyz_tpl_jinja-0.5.1.data/data/share/jupyter/labextensions/@deathbeds/wxyz-tpl-nunjucks/static/remoteEntry.8fc394d0f9814dd4dc28.js
wxyz_tpl_jinja-0.5.1.data/data/share/jupyter/labextensions/@deathbeds/wxyz-tpl-nunjucks/static/style.js
wxyz_tpl_jinja-0.5.1.dist-info/LICENSE.txt
wxyz_tpl_jinja-0.5.1.dist-info/METADATA
wxyz_tpl_jinja-0.5.1.dist-info/WHEEL
wxyz_tpl_jinja-0.5.1.dist-info/top_level.txt
wxyz_tpl_jinja-0.5.1.dist-info/RECORD
